{"cameraMode":{"drawMode":0,"name":"Shaded","section":"Shading Mode"},"sceneLighting":false,"audioPlay":false,"sceneViewState":{"m_AlwaysRefresh":false,"showFog":true,"showSkybox":false,"showFlares":true,"showImageEffects":true,"showParticleSystems":true,"showVisualEffectGraphs":true,"m_FxEnabled":true},"in2DMode":false,"pivot":{"x":0.7643308639526367,"y":0.9176756143569946,"z":1.4757187366485596},"rotation":{"x":-0.011979209259152413,"y":-0.7648234367370606,"z":-0.01423111092299223,"w":0.644016683101654},"size":1.2886967658996583,"orthographic":false}